vs_shortcut/__init__.py
vs_shortcut/__main__.py
vs_shortcut-1.0.1.dist-info/COPYING.txt
vs_shortcut-1.0.1.dist-info/METADATA
vs_shortcut-1.0.1.dist-info/WHEEL
vs_shortcut-1.0.1.dist-info/top_level.txt
vs_shortcut-1.0.1.dist-info/RECORD
