Metadata-Version: 2.1
Name: vs-shortcut
Version: 1.0.1
Summary: A Microsoft Visual Studio shortcut creator for Anaconda-navigator Windows (using menuinst)
Author: Maxime Tousignant-Tremblay
License: AGPL-3.0
Platform: Windows
Classifier: Development Status :: 4 - Beta
Classifier: Programming Language :: Python :: 3.10
Classifier: Programming Language :: Python :: Implementation :: CPython
Classifier: License :: OSI Approved :: GNU Affero General Public License v3 or later (AGPLv3+)
Classifier: Intended Audience :: End Users/Desktop
Classifier: Natural Language :: English
Classifier: Operating System :: Microsoft :: Windows
Classifier: Topic :: Software Development :: User Interfaces
License-File: COPYING.txt
